postit/__init__.py
postit/cli.py
postit/deduper.py
postit/documents.py
postit/examples/__init__.py
postit/examples/news.py
postit/files.py
postit/mixer.py
postit/processor.py
postit/registry.py
postit/taggers/__init__.py
postit/taggers/code/__init__.py
postit/taggers/code/comments.py
postit/taggers/dedupe.py
postit/taggers/length.py
postit/tagging.py
postit/types.py
postit/utils/__init__.py
postit/utils/bloom.py
postit/utils/logging.py
postit/utils/paths.py
postit-0.1.4.dist-info/LICENSE
postit-0.1.4.dist-info/METADATA
postit-0.1.4.dist-info/WHEEL
postit-0.1.4.dist-info/entry_points.txt
postit-0.1.4.dist-info/RECORD
