Metadata-Version: 2.3
Name: postit
Version: 0.1.4
Summary: A robust, extensible Python data tagging framework for dynamic processing and intelligent filtering of pretraining corpora for AI models.
License: Apache-2.0
Author: Brennen Ho
Author-email: postit@brennen.dev
Requires-Python: >=3.12,<4.0
Classifier: License :: OSI Approved :: Apache Software License
Classifier: Programming Language :: Python :: 3
Classifier: Programming Language :: Python :: 3.12
Classifier: Programming Language :: Python :: 3.13
Requires-Dist: bitarray (>=2.9.2,<3.0.0)
Requires-Dist: gcsfs (>=2024.6.1,<2025.0.0)
Requires-Dist: mmh3 (>=4.1.0,<5.0.0)
Requires-Dist: pyyaml (>=6.0.2,<7.0.0)
Requires-Dist: rich (>=13.7.1,<14.0.0)
Requires-Dist: typer (>=0.12.3,<0.13.0)
Project-URL: Homepage, https://github.com/brennenho/post-it
Project-URL: Issues, https://github.com/brennenho/post-it/issues
